strands_xai/__init__.py
strands_xai/_validation.py
strands_xai/py.typed
strands_xai/xai.py
strands_xai-0.1.2.dist-info/METADATA
strands_xai-0.1.2.dist-info/WHEEL
strands_xai-0.1.2.dist-info/licenses/LICENSE
strands_xai-0.1.2.dist-info/RECORD
