Metadata-Version: 2.4
Name: strands-xai
Version: 0.1.2
Summary: xAI model provider for Strands Agents SDK
Project-URL: Homepage, https://github.com/Cerrix/strands-xai
Project-URL: Documentation, https://github.com/Cerrix/strands-xai#readme
Project-URL: Repository, https://github.com/Cerrix/strands-xai
Project-URL: Issues, https://github.com/Cerrix/strands-xai/issues
Author: Francesco Cerizzi
License-Expression: MIT
License-File: LICENSE
Keywords: agents,ai,grok,llm,strands,xai
Classifier: Development Status :: 4 - Beta
Classifier: Intended Audience :: Developers
Classifier: License :: OSI Approved :: MIT License
Classifier: Programming Language :: Python :: 3
Classifier: Programming Language :: Python :: 3.10
Classifier: Programming Language :: Python :: 3.11
Classifier: Programming Language :: Python :: 3.12
Classifier: Programming Language :: Python :: 3.13
Classifier: Programming Language :: Python :: 3.14
Classifier: Topic :: Scientific/Engineering :: Artificial Intelligence
Classifier: Topic :: Software Development :: Libraries :: Python Modules
Requires-Python: >=3.10
Requires-Dist: strands-agents>=1.23.0
Requires-Dist: xai-sdk<2.0.0,>=1.5.0
Provides-Extra: dev
Requires-Dist: build>=0.10.0; extra == 'dev'
Requires-Dist: mypy>=1.0.0; extra == 'dev'
Requires-Dist: pytest-asyncio>=0.21.0; extra == 'dev'
Requires-Dist: pytest-cov>=4.0.0; extra == 'dev'
Requires-Dist: pytest-mock>=3.0.0; extra == 'dev'
Requires-Dist: pytest>=7.0.0; extra == 'dev'
Requires-Dist: ruff>=0.1.0; extra == 'dev'
Requires-Dist: twine>=4.0.0; extra == 'dev'
